calculatorMCP.py
hello_mcp_new-0.1.0.dist-info/METADATA
hello_mcp_new-0.1.0.dist-info/WHEEL
hello_mcp_new-0.1.0.dist-info/top_level.txt
hello_mcp_new-0.1.0.dist-info/RECORD
